fin_maestro_kin/__init__.py
fin_maestro_kin/constants.py
fin_maestro_kin/main.py
fin_maestro_kin/modules/__init__.py
fin_maestro_kin/modules/data_toolkit/__init__.py
fin_maestro_kin/modules/data_toolkit/nse/__init__.py
fin_maestro_kin/modules/data_toolkit/nse/nse_operations.py
fin_maestro_kin/modules/data_toolkit/screener/__init__.py
fin_maestro_kin/modules/data_toolkit/screener/screener_equities.py
fin_maestro_kin/modules/sentiment_analysis/__init__.py
fin_maestro_kin/modules/sentiment_analysis/sentiment_analysis.py
fin_maestro_kin/modules/trend_detector/__init__.py
fin_maestro_kin/modules/trend_detector/trend_detector.py
fin_maestro_kin-0.3.3.dist-info/LICENSE
fin_maestro_kin-0.3.3.dist-info/METADATA
fin_maestro_kin-0.3.3.dist-info/WHEEL
fin_maestro_kin-0.3.3.dist-info/RECORD
