Metadata-Version: 2.1
Name: fin-maestro-kin
Version: 0.3.3
Summary: Seamless Finance: Docker Deployed APIs for Smart Investments.
License: MIT
Author: DEV_FINWIZ
Author-email: devjuneja43@gmail.com
Requires-Python: >=3.9,<4.0
Classifier: License :: OSI Approved :: MIT License
Classifier: Programming Language :: Python :: 3
Classifier: Programming Language :: Python :: 3.9
Classifier: Programming Language :: Python :: 3.10
Classifier: Programming Language :: Python :: 3.11
Classifier: Programming Language :: Python :: 3.12
Requires-Dist: beautifulsoup4 (>=4.12.3,<5.0.0)
Requires-Dist: fastapi (>=0.114.0,<0.115.0)
Requires-Dist: matplotlib (>=3.8.2,<4.0.0)
Requires-Dist: numpy (>=1.26.3,<2.0.0)
Requires-Dist: pandas (>=2.1.4,<3.0.0)
Requires-Dist: pydantic (>=2.5.3,<3.0.0)
Requires-Dist: redis (>=5.0.4,<6.0.0)
Requires-Dist: requests (>=2.31.0,<3.0.0)
Requires-Dist: uvicorn (>=0.25.0,<0.26.0)
Requires-Dist: yfinance (>=0.2.35,<0.3.0)
